{
  "parent": "minecraft:husbandry/fruitfulfun/start",
  "criteria": {
    "_": {
      "conditions": {
        "items": [
          {
            "items": [
              "fruitfulfun:grapefruit_sapling"
            ]
          }
        ]
      },
      "trigger": "minecraft:inventory_changed"
    }
  },
  "display": {
    "announce_to_chat": true,
    "description": {
      "translate": "advancements.fruitfulfun.grapefruit.description"
    },
    "frame": "goal",
    "hidden": false,
    "icon": {
      "item": "fruitfulfun:grapefruit"
    },
    "show_toast": true,
    "title": {
      "translate": "advancements.fruitfulfun.grapefruit.title"
    }
  },
  "requirements": [
    [
      "_"
    ]
  ],
  "rewards": {
    "experience": 100
  },
  "sends_telemetry_event": false
}
